oytel/__init__.py
oytel/client.py
oytel/exceptions.py
oytel/types.py
oytel_esim_sdk-1.0.0.dist-info/licenses/LICENSE
oytel_esim_sdk-1.0.0.dist-info/METADATA
oytel_esim_sdk-1.0.0.dist-info/WHEEL
oytel_esim_sdk-1.0.0.dist-info/top_level.txt
oytel_esim_sdk-1.0.0.dist-info/RECORD
